agenwatch/__init__.py
agenwatch/client.py
agenwatch/llm_provider.py
agenwatch/sdk.py
agenwatch/sdk_adapter.py
agenwatch/sdk_event_adapter.py
agenwatch/sdk_event_sink.py
agenwatch/sdk_events.py
agenwatch/types.py
agenwatch/_kernel/__init__.py
agenwatch/_kernel/agent.py
agenwatch/_kernel/agent_result.py
agenwatch/_kernel/context_manager.py
agenwatch/_kernel/dag_planner.py
agenwatch/_kernel/embedding_service.py
agenwatch/_kernel/errors.py
agenwatch/_kernel/event_types.py
agenwatch/_kernel/execution_contracts.py
agenwatch/_kernel/execution_manager.py
agenwatch/_kernel/fail_fast.py
agenwatch/_kernel/llm_response.py
agenwatch/_kernel/loop_breaker.py
agenwatch/_kernel/memory_extractor.py
agenwatch/_kernel/memory_system.py
agenwatch/_kernel/memory_types.py
agenwatch/_kernel/mock_provider.py
agenwatch/_kernel/observability.py
agenwatch/_kernel/repair_memory.py
agenwatch/_kernel/replay.py
agenwatch/_kernel/retry_manager.py
agenwatch/_kernel/scheduler.py
agenwatch/_kernel/timeline_logger.py
agenwatch/_kernel/universal_llm.py
agenwatch/_kernel/embeddings/__init__.py
agenwatch/_kernel/embeddings/embedding_manager.py
agenwatch/_kernel/memory/__init__.py
agenwatch/_kernel/memory/null_memory.py
agenwatch/_kernel/memory_store/__init__.py
agenwatch/_kernel/memory_store/vector_store.py
agenwatch/_kernel/safety/__init__.py
agenwatch/_kernel/safety/budget_manager.py
agenwatch/_kernel/safety/circuit_breaker.py
agenwatch/_kernel/safety/safety_guard.py
agenwatch/_kernel/sandbox/__init__.py
agenwatch/_kernel/sandbox/tool_sandbox.py
agenwatch/_kernel/testing/__init__.py
agenwatch/_kernel/testing/mock_llm.py
agenwatch/_kernel/tools/__init__.py
agenwatch/_kernel/tools/base.py
agenwatch/_kernel/tools/execution.py
agenwatch/_kernel/tools/function_tool.py
agenwatch/_kernel/tools/merger.py
agenwatch/_kernel/tools/parallel_execution.py
agenwatch/_kernel/tools/registry.py
agenwatch/_kernel/tools/repair_engine.py
agenwatch/_kernel/tools/safety.py
agenwatch/_kernel/tools/schemas.py
agenwatch-0.1.2.dist-info/licenses/LICENSE
agenwatch-0.1.2.dist-info/METADATA
agenwatch-0.1.2.dist-info/WHEEL
agenwatch-0.1.2.dist-info/top_level.txt
agenwatch-0.1.2.dist-info/RECORD
