Metadata-Version: 2.4
Name: agenwatch
Version: 0.1.2
Summary: Runtime-enforced governance kernel for AI agents
Author-email: AgenWatch Team <agenwatch.dev@gmail.com>
License: MIT
Project-URL: Homepage, https://github.com/agenwatch/agenwatch
Project-URL: Repository, https://github.com/agenwatch/agenwatch
Project-URL: Bug Tracker, https://github.com/agenwatch/agenwatch/issues
Keywords: ai,agents,governance,security,llm
Classifier: Development Status :: 4 - Beta
Classifier: Intended Audience :: Developers
Classifier: License :: OSI Approved :: MIT License
Classifier: Programming Language :: Python :: 3
Classifier: Topic :: Software Development :: Libraries :: Python Modules
Requires-Python: >=3.10
License-File: LICENSE
Requires-Dist: pydantic
Requires-Dist: psutil
Requires-Dist: python-dotenv
Requires-Dist: tiktoken
Requires-Dist: litellm
Requires-Dist: openai
Requires-Dist: groq
Dynamic: license-file
